django_bulk_load/__init__.py
django_bulk_load/bulk_load.py
django_bulk_load/django.py
django_bulk_load/queries.py
django_bulk_load/sql_utils.py
django_bulk_load/utils.py
django_bulk_load_modern-2.0.0.dist-info/METADATA
django_bulk_load_modern-2.0.0.dist-info/WHEEL
django_bulk_load_modern-2.0.0.dist-info/licenses/LICENSE
django_bulk_load_modern-2.0.0.dist-info/RECORD
