Metadata-Version: 2.4
Name: django-bulk-load-modern
Version: 2.0.0
Summary: Modern fork of django-bulk-load with psycopg3 support
Project-URL: Homepage, https://github.com/blackbox-innovation/django-bulk-load-modern
Project-URL: Original Project, https://github.com/cedar-team/django-bulk-load
Project-URL: Bug Tracker, https://github.com/blackbox-innovation/django-bulk-load-modern/issues
Author-email: Blackbox Innovation <dev@blackbox.ai>
License: MIT
License-File: LICENSE
Classifier: Development Status :: 4 - Beta
Classifier: Framework :: Django
Classifier: Framework :: Django :: 2.2
Classifier: Framework :: Django :: 3.0
Classifier: Framework :: Django :: 3.1
Classifier: Framework :: Django :: 3.2
Classifier: Framework :: Django :: 4.0
Classifier: Framework :: Django :: 4.1
Classifier: Framework :: Django :: 4.2
Classifier: Framework :: Django :: 5.0
Classifier: Intended Audience :: Developers
Classifier: License :: OSI Approved :: MIT License
Classifier: Operating System :: OS Independent
Classifier: Programming Language :: Python :: 3
Classifier: Programming Language :: Python :: 3.12
Classifier: Topic :: Database
Classifier: Topic :: Software Development :: Libraries :: Python Modules
Requires-Python: >=3.12
Requires-Dist: django>=2.2
Requires-Dist: psycopg>=3.2.9
Provides-Extra: test
